quaestor/__init__.py
quaestor/cli.py
quaestor/constants.py
quaestor/claude/__init__.py
quaestor/claude/agents/__init__.py
quaestor/claude/agents/architect.md
quaestor/claude/agents/debugger.md
quaestor/claude/agents/implementer.md
quaestor/claude/agents/planner.md
quaestor/claude/agents/qa.md
quaestor/claude/agents/refactorer.md
quaestor/claude/agents/researcher.md
quaestor/claude/agents/reviewer.md
quaestor/claude/agents/security.md
quaestor/claude/agents/spec-manager.md
quaestor/claude/agents/speccer.md
quaestor/claude/agents/workflow-coordinator.md
quaestor/claude/commands/__init__.py
quaestor/claude/commands/debug.md
quaestor/claude/commands/impl.md
quaestor/claude/commands/plan.md
quaestor/claude/commands/project-init.md
quaestor/claude/commands/research.md
quaestor/claude/commands/review.md
quaestor/claude/hooks/__init__.py
quaestor/claude/hooks/automation_base.json
quaestor/claude/hooks/base.py
quaestor/claude/hooks/session_context_loader.py
quaestor/claude/hooks/settings_uvx.json
quaestor/claude/hooks/spec_validator.py
quaestor/claude/hooks/todo_spec_progress.py
quaestor/claude/templates/__init__.py
quaestor/claude/templates/architecture.md
quaestor/claude/templates/context.md
quaestor/claude/templates/include.md
quaestor/claude/templates/rules.md
quaestor/cli/__init__.py
quaestor/cli/app.py
quaestor/cli/config.py
quaestor/cli/hooks.py
quaestor/cli/init.py
quaestor/cli/update.py
quaestor/cli/validate.py
quaestor/core/__init__.py
quaestor/core/config_manager.py
quaestor/core/config_schemas.py
quaestor/core/configuration.py
quaestor/core/folder_manager.py
quaestor/core/languages.yaml
quaestor/core/project_analysis.py
quaestor/core/project_metadata.py
quaestor/core/spec_schema.py
quaestor/core/specifications.py
quaestor/core/template_engine.py
quaestor/core/updater.py
quaestor/utils/__init__.py
quaestor/utils/file_utils.py
quaestor/utils/project_detection.py
quaestor/utils/yaml_utils.py
quaestor-0.6.3.dist-info/licenses/LICENSE
quaestor-0.6.3.dist-info/METADATA
quaestor-0.6.3.dist-info/WHEEL
quaestor-0.6.3.dist-info/entry_points.txt
quaestor-0.6.3.dist-info/top_level.txt
quaestor-0.6.3.dist-info/RECORD
