Metadata-Version: 2.4
Name: quaestor
Version: 0.6.3
Summary: AI-assisted development context management tool for maintaining consistency and productivity
Author-email: Jean Luciano <jeanluciano@example.com>
License-Expression: MIT
Project-URL: Homepage, https://github.com/jeanluciano/quaestor
Project-URL: Repository, https://github.com/jeanluciano/quaestor
Project-URL: Issues, https://github.com/jeanluciano/quaestor/issues
Keywords: ai,development,context,claude,project-management,ai-tools
Classifier: Development Status :: 3 - Alpha
Classifier: Intended Audience :: Developers
Classifier: Programming Language :: Python :: 3
Classifier: Programming Language :: Python :: 3.12
Classifier: Topic :: Software Development :: Libraries :: Python Modules
Classifier: Topic :: Software Development :: Quality Assurance
Requires-Python: >=3.12
License-File: LICENSE
Requires-Dist: typer>=0.16.0
Requires-Dist: rich>=13.0.0
Requires-Dist: textual>=1.0.0
Requires-Dist: PyYAML<7.0,>=6.0
Requires-Dist: pydantic>=2.0.0
Dynamic: license-file
